MANIFEST.in
README.txt
setup.cfg
setup.py
asv_imgs/__init__.py
asv_imgs/admin.py
asv_imgs/models.py
asv_imgs/settings.py
asv_imgs/settings_default.py
asv_imgs/urls.py
asv_imgs.egg-info/PKG-INFO
asv_imgs.egg-info/SOURCES.txt
asv_imgs.egg-info/dependency_links.txt
asv_imgs.egg-info/not-zip-safe
asv_imgs.egg-info/requires.txt
asv_imgs.egg-info/top_level.txt
asv_imgs/templates/asv_imgs__admin__img_preview.html
asv_imgs/templates/asv_imgs__admin__stacked.html
asv_imgs/templatetags/__init__.py
asv_imgs/templatetags/asv_imgs_tags.py