Metadata-Version: 1.0
Name: asv-imgs
Version: dev-20120130-01
Summary: 
